pfazuredb/__init__.py
pfazuredb/tools/__init__.py
pfazuredb/tools/mongodbvcore.py
pfazuredb/tools/nosql.py
pfazuredb/tools/postgresqlpgvector.py
pfazuredb/tools/utils.py
pfazuredb/yamls/mongodbvcore.yaml
pfazuredb/yamls/nosql.yaml
pfazuredb/yamls/postgresqlpgvector.yaml
tests/__init__.py
tests/test_mongovcore.py
tests/test_nosql.py
tests/test_postgresql_pgvector.py
pf_azuredb-1.1.0.dist-info/METADATA
pf_azuredb-1.1.0.dist-info/WHEEL
pf_azuredb-1.1.0.dist-info/entry_points.txt
pf_azuredb-1.1.0.dist-info/top_level.txt
pf_azuredb-1.1.0.dist-info/RECORD
