Metadata-Version: 2.1
Name: pf-azuredb
Version: 1.1.0
Summary: Package for use in promptflow for vector search in azure db
Author: Hossein K. Heris and applied ai team@azure data
Requires-Dist: numpy ==1.24.4
Requires-Dist: psycopg2-binary ==2.9.6
Requires-Dist: pymongo ==4.6.1
Requires-Dist: pgvector ==0.2.0
Requires-Dist: azure-cosmos ==4.7.0
